{
  "utc": "2026-07-17T08:10:59.177557+00:00",
  "status": "pass",
  "source_url": "https://earthquake.usgs.gov/earthquakes/feed/v1.0/summary/all_day.csv",
  "source_note": "US Government work \u2014 public domain (17 U.S.C. \u00a7 105); no personal data.",
  "http_status": 200,
  "input_bytes": 53374,
  "input_sha256": "83fb44bf2c165c573a162ea02b06ba7416757242c11b6aace7ea39c6e85577e4",
  "input_rows": 264,
  "table": "earthquakes",
  "ledger_verified": true,
  "pipeline_returncode": 0,
  "version": "4.37.0"
}
